eft/Color.py
eft/Theme.py
eft/__init__.py
eft_py-2.0.0.dist-info/LICENSE
eft_py-2.0.0.dist-info/METADATA
eft_py-2.0.0.dist-info/WHEEL
eft_py-2.0.0.dist-info/top_level.txt
eft_py-2.0.0.dist-info/RECORD
