Metadata-Version: 2.1
Name: eft-py
Version: 2.0.0
Summary: A python library for easily creating themes for your applications.
Author: Possible Panda
Classifier: Development Status :: 3 - Alpha
Classifier: Intended Audience :: Developers
Classifier: License :: OSI Approved :: MIT License
Classifier: Programming Language :: Python :: 3.12
License-File: LICENSE
